rnxcovpy/__init__.py
rnxcovpy/element.py
rnxcovpy/obs211to302.py
rnxcovpy/obs211to304.py
rnxcovpy/obs211to305.py
rnxcovpy/obs302to211.py
rnxcovpy/obs302to304.py
rnxcovpy/obs302to305.py
rnxcovpy/obs304to211.py
rnxcovpy/obs304to305.py
rnxcovpy/obs305to211.py
rnxcovpy-0.1.2.dist-info/LICENSE
rnxcovpy-0.1.2.dist-info/METADATA
rnxcovpy-0.1.2.dist-info/WHEEL
rnxcovpy-0.1.2.dist-info/top_level.txt
rnxcovpy-0.1.2.dist-info/RECORD
