Metadata-Version: 2.1
Name: rnxcovpy
Version: 0.1.2
Summary: This package can be used to convert betueen different versions of the RINEX format.
Home-page: UNKNOWN
Author: MingGao
Author-email: 2752889603@qq.com
License: MIT
Platform: UNKNOWN
Classifier: Programming Language :: Python :: 3
Classifier: License :: OSI Approved :: MIT License
Requires-Python: >=3.6
